cobrakbase/AbstractHandleClient.py
cobrakbase/__init__.py
cobrakbase/exceptions.py
cobrakbase/kbase_object_info.py
cobrakbase/kbase_workspace.py
cobrakbase/kbaseapi.py
cobrakbase/kbaseapi_cache.py
cobrakbase/Workspace/WorkspaceClient.py
cobrakbase/Workspace/__init__.py
cobrakbase/Workspace/authclient.py
cobrakbase/Workspace/baseclient.py
cobrakbase/core/__init__.py
cobrakbase/core/build_metabolic_model.py
cobrakbase/core/cobra_to_kbase.py
cobrakbase/core/converters.py
cobrakbase/core/fba_utilities.py
cobrakbase/core/kbase_fba_builder.py
cobrakbase/core/kbase_model_builder.py
cobrakbase/core/kbase_object_factory.py
cobrakbase/core/kbase_types.py
cobrakbase/core/kbasebiochemmedia.py
cobrakbase/core/kbasefbafba.py
cobrakbase/core/kbasefbatemplate.py
cobrakbase/core/kbasegenomes_feature.py
cobrakbase/core/kbasegenomesgenome.py
cobrakbase/core/kbaseobject.py
cobrakbase/core/model.py
cobrakbase/core/utils.py
cobrakbase/core/kbasebiochem/__init__.py
cobrakbase/core/kbasebiochem/media.py
cobrakbase/core/kbaseclassifier/__init__.py
cobrakbase/core/kbaseclassifier/genomeclassifier.py
cobrakbase/core/kbaseclassifier/genomeclassifiertrainingset.py
cobrakbase/core/kbaseexperiments/__init__.py
cobrakbase/core/kbaseexperiments/attributemapping.py
cobrakbase/core/kbasefba/__init__.py
cobrakbase/core/kbasefba/eschermap.py
cobrakbase/core/kbasefba/fba.py
cobrakbase/core/kbasefba/fbamodel.py
cobrakbase/core/kbasefba/fbamodel_biomass.py
cobrakbase/core/kbasefba/fbamodel_builder.py
cobrakbase/core/kbasefba/fbamodel_from_cobra.py
cobrakbase/core/kbasefba/fbamodel_metabolite.py
cobrakbase/core/kbasefba/fbamodel_protein.py
cobrakbase/core/kbasefba/fbamodel_reaction.py
cobrakbase/core/kbasefba/fbamodel_validator.py
cobrakbase/core/kbasefba/newmodeltemplate.py
cobrakbase/core/kbasefba/newmodeltemplate_builder.py
cobrakbase/core/kbasefba/newmodeltemplate_complex.py
cobrakbase/core/kbasefba/newmodeltemplate_metabolite.py
cobrakbase/core/kbasefba/newmodeltemplate_reaction.py
cobrakbase-0.3.0.dist-info/LICENSE.md
cobrakbase-0.3.0.dist-info/METADATA
cobrakbase-0.3.0.dist-info/WHEEL
cobrakbase-0.3.0.dist-info/top_level.txt
cobrakbase-0.3.0.dist-info/zip-safe
cobrakbase-0.3.0.dist-info/RECORD
